PriyalSingla_102103274/__init__.py
Priyal_102103274-0.2.dist-info/LICENSE.txt
Priyal_102103274-0.2.dist-info/METADATA
Priyal_102103274-0.2.dist-info/WHEEL
Priyal_102103274-0.2.dist-info/top_level.txt
Priyal_102103274-0.2.dist-info/RECORD
