Metadata-Version: 2.1
Name: Priyal-102103274
Version: 0.2
Summary: A python package for implementing topsis
Author: Priyal Singla
Author-email: psingla3_be21@thapar.edu
Classifier: Programming Language :: Python :: 3
Classifier: License :: OSI Approved :: MIT License
Classifier: Operating System :: OS Independent
License-File: LICENSE.txt
